similarweb_rapidapi/__init__.py
similarweb_rapidapi/api.py
similarweb_rapidapi/logger_mock.py
similarweb_rapidapi/schemas/__init__.py
similarweb_rapidapi/schemas/additional_domain_data.py
similarweb_rapidapi/schemas/base.py
similarweb_rapidapi/schemas/basic_domain_data.py
similarweb_rapidapi/schemas/cancel_task.py
similarweb_rapidapi/schemas/complete_data_task.py
similarweb_rapidapi/schemas/my_tasks.py
similarweb_rapidapi/schemas/task.py
similarweb_rapidapi/schemas/task_status.py
similarweb_rapidapi-0.1.4.dist-info/METADATA
similarweb_rapidapi-0.1.4.dist-info/WHEEL
similarweb_rapidapi-0.1.4.dist-info/top_level.txt
similarweb_rapidapi-0.1.4.dist-info/RECORD
