Metadata-Version: 2.1
Name: similarweb_rapidapi
Version: 0.1.4
Summary: SimilarWeb API on RapidAPI
Home-page: https://letsscrape.com/scrapers/similarweb-api/
Author: LetsScrape
Author-email: hello@letsscrape.com
Project-URL: Documentation, https://rapidapi.com/letsscrape/api/similarweb-working-api
Project-URL: Bug Reports, https://github.com/letsscrape/python_similarweb_rapidapi/issues
Project-URL: Source Code, https://github.com/letsscrape/python_similarweb_rapidapi
Keywords: rapidapi,similarweb,similarweb api,scraping,parsing,scraper
